{
  "response": [
    {
      "maintainer": "nhansp ft. yuuki",
      "oem": "Google",
      "device": "Pixel 6a",
      "filename": "EvolutionX-14.0-20241007-bluejay-v9.4-Unofficial.zip",
      "download": "https://pub-4a686e4731f74758ab53df526a4fe7da.r2.dev/EvolutionX-14.0-20241007-bluejay-v9.4-Unofficial.zip",
      "timestamp": 1728246745,
      "md5": "718c91db910fe19ddff74e0b51bcfe50",
      "sha256": "33a98b86e9d29e231de87c772f63d3ecaa839a47ed2e89a0f1f9bfd1605fa1b2",
      "size": 2566546663,
      "version": "9.4",
      "buildtype": "05.20",
      "forum": "https://tvyiutnhisokewt.github.io/bluejay",
      "firmware": "",
      "paypal": "",
      "telegram": ""
    }
  ]
}
